segviz/__init__.py
segviz/render.py
segviz/template.html
segviz/utils.py
segviz-3.1.2.data/scripts/convert_nii
segviz-3.1.2.data/scripts/create_checkerboard
segviz-3.1.2.data/scripts/generate_html
segviz-3.1.2.data/scripts/run_html
segviz-3.1.2.dist-info/LICENSE.txt
segviz-3.1.2.dist-info/METADATA
segviz-3.1.2.dist-info/WHEEL
segviz-3.1.2.dist-info/top_level.txt
segviz-3.1.2.dist-info/RECORD
