Metadata-Version: 2.1
Name: segviz
Version: 3.1.2
Summary: Show the image and label image overlay.
Home-page: https://github.com/shuohan/segviz
Author: Shuo Han
Author-email: shuohanthu@gmail.com
License: MIT
Platform: UNKNOWN
Classifier: Programming Language :: Python :: 3
Classifier: License :: OSI Approved :: MIT License
Classifier: Operating System :: OS Independent
Requires-Python: >=3.7
Requires-Dist: numpy
Requires-Dist: scipy
Requires-Dist: Pillow
Requires-Dist: improc3d
Requires-Dist: jinja2
Requires-Dist: flask
Requires-Dist: nibabel
